recover/__init__.py
zh_recover-1.2.0.dist-info/DESCRIPTION.rst
zh_recover-1.2.0.dist-info/METADATA
zh_recover-1.2.0.dist-info/RECORD
zh_recover-1.2.0.dist-info/WHEEL
zh_recover-1.2.0.dist-info/entry_points.txt
zh_recover-1.2.0.dist-info/metadata.json
zh_recover-1.2.0.dist-info/top_level.txt
